argmatch/__init__.py
argmatch/_compat.py
argmatch/attributes.py
argmatch/base.py
argmatch/collections.py
argmatch/functions.py
argmatch/general.py
argmatch/numbers.py
argmatch/objects.py
argmatch/operators.py
argmatch/strings.py
argmatch/types.py
argmatch-1.0.3.dist-info/METADATA
argmatch-1.0.3.dist-info/WHEEL
argmatch-1.0.3.dist-info/licenses/LICENSE
argmatch-1.0.3.dist-info/RECORD
