Metadata-Version: 2.4
Name: argmatch
Version: 1.0.3
Summary: 
License-File: LICENSE
Author: Matt Gilene
Author-email: mdgilene@gmail.com
Requires-Python: >=3.10,<4.0
Classifier: Development Status :: 3 - Alpha
Classifier: Intended Audience :: Developers
Classifier: License :: OSI Approved :: BSD License
Classifier: Operating System :: OS Independent
Classifier: Programming Language :: Python
Classifier: Programming Language :: Python :: 3
Classifier: Programming Language :: Python :: 3.10
Classifier: Programming Language :: Python :: 3.11
Classifier: Programming Language :: Python :: 3.12
Classifier: Programming Language :: Python :: 3.13
Classifier: Programming Language :: Python :: 3.14
Classifier: Programming Language :: Python :: Implementation :: CPython
Classifier: Programming Language :: Python :: Implementation :: PyPy
Classifier: Topic :: Software Development :: Testing
Project-URL: Documentation, https://argmatch.readthedocs.io
Project-URL: Homepage, https://github.com/mdgilene/argmatch
Project-URL: Issues, https://github.com/mdgilene/argmatch/issues
Project-URL: Repository, https://github.com/mdgilene/argmatch
